rpvputil/__init__.py
rpvputil/cutil.py
rpvputil/hutil.py
rpvputil/mutil.py
rpvputil/outil.py
rpvputil/qutil.py
rpvputil/rutil.py
rpvputil/test.py
rpvputil/times.py
rpvputil/uutil.py
rpvputil/webutil.py
rpvputil/wutil.py
rpvputil/common/__init__.py
rpvputil/common/abstractimageuploadform.py
rpvputil/common/abstractmiddleware.py
rpvputil/util/__init__.py
rpvputil/util/abstractutil.py
rpvputil-2.5.1.dist-info/LICENSE
rpvputil-2.5.1.dist-info/METADATA
rpvputil-2.5.1.dist-info/WHEEL
rpvputil-2.5.1.dist-info/top_level.txt
rpvputil-2.5.1.dist-info/RECORD
