Metadata-Version: 2.1
Name: rpvputil
Version: 2.5.1
Summary: Comprehensive toolkit for time, string, random number, encryption, and more
Author-email: pingabc <pingabc163@163.com>
Classifier: Programming Language :: Python :: 3
Classifier: License :: OSI Approved :: MIT License
Classifier: Operating System :: OS Independent
Requires-Python: >=3
License-File: LICENSE
